flask_jsonschemer.py
Flask_JsonSchemer-0.0.1.dist-info/DESCRIPTION.rst
Flask_JsonSchemer-0.0.1.dist-info/METADATA
Flask_JsonSchemer-0.0.1.dist-info/RECORD
Flask_JsonSchemer-0.0.1.dist-info/WHEEL
Flask_JsonSchemer-0.0.1.dist-info/metadata.json
Flask_JsonSchemer-0.0.1.dist-info/top_level.txt
