Metadata-Version: 2.0
Name: Flask-JsonSchemer
Version: 0.0.1
Summary: Flask extension for validating JSON requets
Home-page: https://github.com/juztin/flask-jsonschemer
Author: Matt Wright, Justin Wilson
Author-email: matt@nobien.net, jsonschemer@minty.io
License: MIT
Platform: any
Classifier: Development Status :: 4 - Beta
Classifier: Environment :: Web Environment
Classifier: Intended Audience :: Developers
Classifier: License :: OSI Approved :: BSD License
Classifier: Operating System :: OS Independent
Classifier: Programming Language :: Python
Classifier: Topic :: Internet :: WWW/HTTP :: Dynamic Content
Classifier: Topic :: Software Development :: Libraries :: Python Modules
Requires-Dist: Flask (>=0.9)
Requires-Dist: jsonschema (>=2.5.1)
